darts/CHANGELOG.md
darts/IPhreeqc.dll
darts/__init__.py
darts/build_info.txt
darts/discretizer.cp39-win_amd64.pyd
darts/engines.cp39-win_amd64.pyd
darts/msvcp140.dll
darts/print_build_info.py
darts/vcomp140.dll
darts/vcruntime140.dll
darts/input/__init__.py
darts/input/input_data.py
darts/models/__init__.py
darts/models/cicd_model.py
darts/models/darts_model.py
darts/models/output.py
darts/models/thmc_model.py
darts/models/opt/__init__.py
darts/models/opt/opt_module_settings.py
darts/physics/__init__.py
darts/physics/blackoil.py
darts/physics/deadoil.py
darts/physics/base/__init__.py
darts/physics/base/operators_base.py
darts/physics/base/physics_base.py
darts/physics/base/property_base.py
darts/physics/geothermal/__init__.py
darts/physics/geothermal/geothermal.py
darts/physics/geothermal/operator_evaluator.py
darts/physics/geothermal/physics.py
darts/physics/geothermal/property_container.py
darts/physics/mech/__init__.py
darts/physics/mech/poroelasticity.py
darts/physics/properties/__init__.py
darts/physics/properties/basic.py
darts/physics/properties/black_oil.py
darts/physics/properties/conductivity.py
darts/physics/properties/density.py
darts/physics/properties/enthalpy.py
darts/physics/properties/eos_properties.py
darts/physics/properties/flash.py
darts/physics/properties/kinetics.py
darts/physics/properties/viscosity.py
darts/physics/properties/iapws/__init__.py
darts/physics/properties/iapws/custom_rock_property.py
darts/physics/properties/iapws/iapws_property.py
darts/physics/properties/iapws/iapws_property_vec.py
darts/physics/super/__init__.py
darts/physics/super/initialize.py
darts/physics/super/operator_evaluator.py
darts/physics/super/physics.py
darts/physics/super/property_container.py
darts/reservoirs/__init__.py
darts/reservoirs/cpg_reservoir.py
darts/reservoirs/reservoir_base.py
darts/reservoirs/struct_reservoir.py
darts/reservoirs/unstruct_reservoir.py
darts/reservoirs/unstruct_reservoir_mech.py
darts/reservoirs/mesh/__init__.py
open_darts-1.3.2.dist-info/LICENSE
open_darts-1.3.2.dist-info/LICENSE.md
open_darts-1.3.2.dist-info/METADATA
open_darts-1.3.2.dist-info/WHEEL
open_darts-1.3.2.dist-info/entry_points.txt
open_darts-1.3.2.dist-info/top_level.txt
open_darts-1.3.2.dist-info/RECORD
