Metadata-Version: 2.1
Name: open-darts
Version: 1.3.2
Summary: Open Delft Advanced Research Terra Simulator
Author-email: Denis Voskov <D.V.Voskov@tudelft.nl>
Maintainer-email: Ilshat Saifullin <i.s.saifullin@tudelft.nl>
License: LICENSE.md
Project-URL: homepage, https://darts.citg.tudelft.nl/
Project-URL: repository, https://gitlab.com/open-darts/open-darts
Project-URL: documentation, https://open-darts.readthedocs.io/en/docs
Keywords: energy transition,modeling of CO2 sequestration,geothermal energy production
Classifier: Programming Language :: Python :: 3
Classifier: Programming Language :: C++
Requires-Python: >=3.9
License-File: LICENSE
License-File: LICENSE.md
Requires-Dist: numba
Requires-Dist: scipy
Requires-Dist: pandas
Requires-Dist: meshio
Requires-Dist: gmsh (<=4.13)
Requires-Dist: iapws
Requires-Dist: openpyxl
Requires-Dist: pyevtk
Requires-Dist: matplotlib
Requires-Dist: vtk
Requires-Dist: shapely
Requires-Dist: igraph
Requires-Dist: sympy
Requires-Dist: opmcpg
Requires-Dist: xarray
Requires-Dist: netCDF4
Requires-Dist: h5py
Requires-Dist: open-darts-flash
Requires-Dist: phreeqpy
Provides-Extra: dev
Requires-Dist: flake8 ; extra == 'dev'
Requires-Dist: black ; extra == 'dev'
Requires-Dist: isort ; extra == 'dev'
Provides-Extra: docs
Requires-Dist: myst-parser ; extra == 'docs'
Requires-Dist: sphinx-rtd-theme ; extra == 'docs'
Requires-Dist: sphinx ; extra == 'docs'
Requires-Dist: sphinx-tabs ; extra == 'docs'
Requires-Dist: sphinx-inline-tabs ; extra == 'docs'
Requires-Dist: sphinxcontrib-matlabdomain ; extra == 'docs'
Requires-Dist: sphinxcontrib-bibtex ; extra == 'docs'
Requires-Dist: linkify-it-py ; extra == 'docs'
Requires-Dist: sphinx-copybutton ; extra == 'docs'
